wagtailiconchooser/__init__.py
wagtailiconchooser/admin.py
wagtailiconchooser/apps.py
wagtailiconchooser/blocks.py
wagtailiconchooser/models.py
wagtailiconchooser/tests.py
wagtailiconchooser/utils.py
wagtailiconchooser/views.py
wagtailiconchooser/widgets.py
wagtailiconchooser/migrations/__init__.py
wagtailiconchooser/static/wagtailiconchooser/css/icon-chooser-widget.css
wagtailiconchooser/static/wagtailiconchooser/js/icon-chooser-widget-controller.js
wagtailiconchooser/static/wagtailiconchooser/js/icon-chooser-widget-telepath.js
wagtailiconchooser/static/wagtailiconchooser/js/icon-chooser-widget.js
wagtailiconchooser/templates/wagtailiconchooser/widgets/icon-chooser-widget.html
wagtailiconchooser/templatetags/__init__.py
wagtailiconchooser/templatetags/wagtailiconchooser_tags.py
wagtail_icon_chooser-0.3.1.dist-info/METADATA
wagtail_icon_chooser-0.3.1.dist-info/WHEEL
wagtail_icon_chooser-0.3.1.dist-info/top_level.txt
wagtail_icon_chooser-0.3.1.dist-info/RECORD
