Metadata-Version: 2.2
Name: wagtail-icon-chooser
Version: 0.3.1
Summary: Wagtail Icon Chooser
Home-page: https://github.com/erick-otenyo/wagtail-icon-chooser
Author: Erick Otenyo
Author-email: otenyo.erick@gmail.com
License: MIT
Classifier: Development Status :: 3 - Alpha
Classifier: Environment :: Web Environment
Classifier: Intended Audience :: Developers
Classifier: License :: OSI Approved :: MIT License
Classifier: Operating System :: OS Independent
Classifier: Programming Language :: Python :: 3 :: Only
Classifier: Programming Language :: Python :: 3.9
Classifier: Programming Language :: Python :: Implementation :: CPython
Classifier: Topic :: Software Development :: Libraries :: Application Frameworks
Classifier: Topic :: Software Development :: Libraries :: Python Modules
Requires-Python: >=3.9
Requires-Dist: wagtail>=6.0
